django_query_tools/__init__.py
django_query_tools/client.py
django_query_tools/server.py
django_query_tools/version.py
django_query_tools-0.3.3.dist-info/LICENSE
django_query_tools-0.3.3.dist-info/METADATA
django_query_tools-0.3.3.dist-info/WHEEL
django_query_tools-0.3.3.dist-info/top_level.txt
django_query_tools-0.3.3.dist-info/RECORD
