Metadata-Version: 2.1
Name: django-query-tools
Version: 0.3.3
Author: Thomas Brier
License-File: LICENSE
